Metadata-Version: 2.1
Name: paraphase
Version: 3.4.0
Summary: paraphase: HiFi-based caller for highly homologous genes
Home-page: https://github.com/PacificBiosciences/paraphase
Author: Xiao Chen
Author-email: xchen@pacificbiosciences.com
License: BSD-3-Clause-Clear
License-File: LICENSE.md
Requires-Dist: pysam
Requires-Dist: numpy
Requires-Dist: scipy
Requires-Dist: networkx
Requires-Dist: matplotlib
Requires-Dist: pyyaml
